{
  "checkpoints": [
    {
      "trainable_name": "PPO",
      "trial_id": "0d7692be",
      "config": {
        "num_workers": 8,
        "num_envs_per_worker": 1,
        "sample_batch_size": 200,
        "batch_mode": "truncate_episodes",
        "num_gpus": 0,
        "train_batch_size": 45,
        "model": {
          "conv_filters": null,
          "conv_activation": "relu",
          "fcnet_activation": "tanh",
          "fcnet_hiddens": [
            64,
            64,
            64
          ],
          "free_log_std": false,
          "no_final_linear": false,
          "vf_share_layers": true,
          "use_lstm": false,
          "max_seq_len": 20,
          "lstm_cell_size": 256,
          "lstm_use_prev_action_reward": false,
          "state_shape": null,
          "framestack": true,
          "dim": 84,
          "grayscale": false,
          "zero_mean": true,
          "custom_preprocessor": null,
          "custom_model": null,
          "custom_action_dist": null,
          "custom_options": {}
        },
        "optimizer": {},
        "gamma": 0.999,
        "horizon": 15,
        "soft_horizon": false,
        "no_done_at_end": false,
        "env_config": {
          "flow_params": "{\n    \"env\": {\n        \"additional_params\": {\n            \"detection_interval\": [\n                0,\n                15,\n                0\n            ],\n            \"num_advanced\": 1,\n            \"num_incoming_edges_per_node\": 4,\n            \"num_measures\": 2,\n            \"num_stopbars\": 3,\n            \"observed_nodes\": [\n                3386,\n                3371,\n                3362,\n                3373\n            ],\n            \"replication_list\": [\n                \"Replication 8050297\",\n                \"Replication 8050315\",\n                \"Replication 8050322\"\n            ],\n            \"statistical_interval\": [\n                0,\n                15,\n                0\n            ],\n            \"target_nodes\": [\n                3369,\n                3341,\n                3370,\n                3344,\n                3329\n            ]\n        },\n        \"clip_actions\": true,\n        \"evaluate\": false,\n        \"horizon\": 16874,\n        \"sims_per_step\": 1125,\n        \"warmup_steps\": 1\n    },\n    \"env_name\": \"coordinated_lights.CoordinatedEnv\",\n    \"exp_tag\": \"coordinated_traffic_lights\",\n    \"initial\": {\n        \"additional_params\": {},\n        \"bunching\": 0,\n        \"edges_distribution\": \"all\",\n        \"lanes_distribution\": Infinity,\n        \"min_gap\": 0,\n        \"perturbation\": 0.0,\n        \"shuffle\": false,\n        \"spacing\": \"uniform\",\n        \"x0\": 0\n    },\n    \"net\": {\n        \"additional_params\": {},\n        \"inflows\": {\n            \"_InFlows__flows\": []\n        },\n        \"osm_path\": null,\n        \"template\": \"/home/damian/flow/examples/aimsun/traffic_light_coordination/scenario_one_hour.ang\"\n    },\n    \"network\": \"coordinated_lights.CoordinatedNetwork\",\n    \"sim\": {\n        \"centroid_config_name\": \"Centroid Configuration 8040652\",\n        \"color_vehicles\": true,\n        \"emission_path\": null,\n        \"experiment_name\": \"Micro SRC Experiment 867\",\n        \"network_name\": \"Dynamic Scenario 866\",\n        \"pxpm\": 2,\n        \"render\": false,\n        \"replication_name\": \"Replication 8050297\",\n        \"restart_instance\": false,\n        \"save_render\": false,\n        \"show_radius\": false,\n        \"sight_radius\": 25,\n        \"sim_step\": 0.8,\n        \"subnetwork_name\": null\n    },\n    \"simulator\": \"aimsun\",\n    \"veh\": []\n}",
          "run": "PPO"
        },
        "env": "CoordinatedEnv-v0",
        "clip_rewards": null,
        "clip_actions": false,
        "preprocessor_pref": "deepmind",
        "lr": 0.0005,
        "monitor": false,
        "log_level": "WARN",
        "callbacks": {
          "on_episode_start": null,
          "on_episode_step": null,
          "on_episode_end": null,
          "on_sample_end": null,
          "on_train_result": null,
          "on_postprocess_traj": null
        },
        "ignore_worker_failures": false,
        "log_sys_usage": true,
        "eager": false,
        "eager_tracing": false,
        "no_eager_on_workers": false,
        "evaluation_interval": null,
        "evaluation_num_episodes": 10,
        "evaluation_config": {},
        "sample_async": false,
        "observation_filter": "NoFilter",
        "synchronize_filters": true,
        "tf_session_args": {
          "intra_op_parallelism_threads": 2,
          "inter_op_parallelism_threads": 2,
          "gpu_options": {
            "allow_growth": true
          },
          "log_device_placement": false,
          "device_count": {
            "CPU": 1
          },
          "allow_soft_placement": true
        },
        "local_tf_session_args": {
          "intra_op_parallelism_threads": 8,
          "inter_op_parallelism_threads": 8
        },
        "compress_observations": false,
        "collect_metrics_timeout": 180,
        "metrics_smoothing_episodes": 100,
        "remote_worker_envs": false,
        "remote_env_batch_wait_ms": 0,
        "min_iter_time_s": 0,
        "timesteps_per_iteration": 0,
        "seed": null,
        "num_cpus_per_worker": 1,
        "num_gpus_per_worker": 0,
        "custom_resources_per_worker": {},
        "num_cpus_for_driver": 1,
        "memory": 0,
        "object_store_memory": 0,
        "memory_per_worker": 0,
        "object_store_memory_per_worker": 0,
        "input": "sampler",
        "input_evaluation": [
          "is",
          "wis"
        ],
        "postprocess_inputs": false,
        "shuffle_buffer_size": 0,
        "output": null,
        "output_compress_columns": [
          "obs",
          "new_obs"
        ],
        "output_max_file_size": 67108864,
        "multiagent": {
          "policies": {},
          "policy_mapping_fn": null,
          "policies_to_train": null
        },
        "use_gae": true,
        "lambda": 0.97,
        "kl_coeff": 0.2,
        "sgd_minibatch_size": 45,
        "shuffle_sequences": true,
        "num_sgd_iter": 10,
        "lr_schedule": null,
        "vf_share_layers": false,
        "vf_loss_coeff": 1.0,
        "entropy_coeff": 0.0,
        "entropy_coeff_schedule": null,
        "clip_param": 0.3,
        "vf_clip_param": 10.0,
        "grad_clip": null,
        "kl_target": 0.02,
        "simple_optimizer": false
      },
      "local_dir": "/home/damian/ray_results/coordinated_traffic_lights",
      "evaluated_params": {},
      "experiment_tag": "0",
      "address": {
        "_type": "CLOUDPICKLE_FALLBACK",
        "value": "8004953a000000000000008c0e7261792e74756e652e747269616c948c084c6f636174696f6e9493942981947d94288c08686f73746e616d65944e8c03706964944e75622e"
      },
      "resources": {
        "cpu": 1,
        "gpu": 0,
        "memory": 0,
        "object_store_memory": 0,
        "extra_cpu": 8,
        "extra_gpu": 0,
        "extra_memory": 0,
        "extra_object_store_memory": 0,
        "custom_resources": {},
        "extra_custom_resources": {}
      },
      "stopping_criterion": {
        "training_iteration": 1000
      },
      "loggers": "80044e2e",
      "sync_to_driver_fn": "80044e2e",
      "verbose": true,
      "max_failures": 999,
      "last_result": {},
      "last_update_time": -Infinity,
      "checkpoint_freq": 1,
      "checkpoint_at_end": true,
      "metric_analysis": {},
      "sync_on_checkpoint": true,
      "checkpoint_manager": {
        "_type": "CLOUDPICKLE_FALLBACK",
        "value": "80049516010000000000008c1b7261792e74756e652e636865636b706f696e745f6d616e61676572948c11436865636b706f696e744d616e616765729493942981947d94288c146b6565705f636865636b706f696e74735f6e756d944b038c165f636865636b706f696e745f73636f72655f6465736394898c165f636865636b706f696e745f73636f72655f61747472948c12747261696e696e675f697465726174696f6e948c116e65776573745f636865636b706f696e749468008c0a436865636b706f696e749493942981947d94288c0773746f72616765948c046469736b948c0576616c7565944e8c06726573756c74947d9475628c115f626573745f636865636b706f696e7473945d948c0b5f6d656d62657273686970948f9475622e"
      },
      "export_formats": [],
      "status": "RUNNING",
      "start_time": 1619612829.8362873,
      "logdir": "/home/damian/ray_results/coordinated_traffic_lights/PPO_CoordinatedEnv-v0_0d7692be_2021-04-28_20-27-0987nor6y0",
      "runner": null,
      "result_logger": null,
      "last_debug": 0,
      "error_file": null,
      "error_msg": null,
      "num_failures": 0,
      "custom_trial_name": null,
      "results": "80044e2e",
      "best_result": "80044e2e",
      "param_config": "80044e2e",
      "extra_arg": "80044e2e",
      "_nonjson_fields": [
        "checkpoint",
        "loggers",
        "sync_to_driver_fn",
        "results",
        "best_result",
        "param_config",
        "extra_arg"
      ],
      "checkpoint": "80044e2e",
      "__logger_started__": true
    }
  ],
  "runner_data": {
    "_global_time_limit": Infinity,
    "_total_time": 0,
    "_iteration": 0,
    "_verbose": true,
    "_server_port": 4321,
    "_local_checkpoint_dir": "/home/damian/ray_results/coordinated_traffic_lights",
    "_remote_checkpoint_dir": null,
    "_resumed": false,
    "_start_time": 1619612829.7201636,
    "_last_checkpoint_time": 1619612829.8704352,
    "_checkpoint_period": 10,
    "_session_str": "2021-04-28_20-27-09",
    "checkpoint_file": "/home/damian/ray_results/coordinated_traffic_lights/experiment_state-2021-04-28_20-27-09.json",
    "launch_web_server": false
  },
  "stats": {
    "start_time": 1619612829.7201636,
    "timestamp": 1619612829.8704352
  }
}